algomancy_data/__init__.py
algomancy_data/datamanager.py
algomancy_data/datasource.py
algomancy_data/etl.py
algomancy_data/extractor.py
algomancy_data/file.py
algomancy_data/inputfileconfiguration.py
algomancy_data/loader.py
algomancy_data/py.typed
algomancy_data/schema.py
algomancy_data/transformer.py
algomancy_data/validator.py
algomancy_data-0.3.18.dist-info/WHEEL
algomancy_data-0.3.18.dist-info/METADATA
algomancy_data-0.3.18.dist-info/RECORD
