Metadata-Version: 2.3
Name: algomancy-data
Version: 0.3.18
Summary: Data management model for the Algomancy library
Author: Pepijn Wissing
Author-email: Pepijn Wissing <Wsg@cqm.nl>
Requires-Dist: pandas
Requires-Dist: openpyxl>=3.1.5
Requires-Dist: algomancy-utils
Requires-Dist: strenum>=0.4.15
Requires-Python: >=3.14
